static_globals-0.0.3.dist-info/METADATA
static_globals-0.0.3.dist-info/LICENSE
static_globals-0.0.3.dist-info/RECORD
static_globals-0.0.3.dist-info/WHEEL
static_globals-0.0.3.dist-info/top_level.txt
test/__init__.py
test/globalize_test.py
static_globals/make-globals-static
static_globals/__init__.py
static_globals/instrumenter.py
static_globals/py.typed
