Metadata-Version: 2.1
Name: static_globals
Version: 0.0.3
Summary: A C/C++ code instrumenter makes global variables static
Home-page: https://github.com/DeadCodeProductions/static_globals
Author: Theodoros Theodoridis
Author-email: theodort@inf.ethz.ch
License: Apache License 2.0
Classifier: Programming Language :: Python :: 3
Requires-Python: >=3.10
License-File: LICENSE
Requires-Dist: diopter >=0.0.29
